[
  {
    "title": "More-than-human practices in wild animal farming: The case of China's forest frogs",
    "authors": [
      "Jin Qian",
      "Annah Zhu",
      "Arjen Buijs",
      "Simon Bush"
    ],
    "year": 2026,
    "venue": "Journal of Rural Studies",
    "doi": "10.1016/j.jrurstud.2026.104172",
    "url": "https://doi.org/10.1016/j.jrurstud.2026.104172",
    "type": "journal-article"
  },
  {
    "title": "Governing food systems to conserve China’s endangered wild animals",
    "authors": [
      "Jin Qian",
      "Annah Lake Zhu",
      "Arjen Buijs",
      "Simon R. Bush"
    ],
    "year": 2025,
    "venue": "One Earth",
    "doi": "10.1016/j.oneear.2025.101276",
    "url": "https://doi.org/10.1016/j.oneear.2025.101276",
    "type": "journal-article"
  },
  {
    "title": "China’s nature-based solutions in the Global South: Evidence from Asia, Africa, and Latin America",
    "authors": [
      "Annah Lake Zhu",
      "Niklas Weins",
      "Juliet Lu",
      "Tyler Harlan",
      "Jin Qian",
      "Fabiana Barbi Seleguim"
    ],
    "year": 2024,
    "venue": "Global Environmental Change",
    "doi": "10.1016/j.gloenvcha.2024.102842",
    "url": "https://doi.org/10.1016/j.gloenvcha.2024.102842",
    "type": "journal-article"
  },
  {
    "title": "Perceptions of COVID-19 origins and China’s wildlife policy reforms",
    "authors": [
      "Annah Lake Zhu",
      "Ruishan Chen",
      "Jessica Rizzolo",
      "Jin Qian"
    ],
    "year": 2023,
    "venue": "Global Ecology and Conservation",
    "doi": "10.1016/j.gecco.2023.e02463",
    "url": "http://dx.doi.org/10.1016/j.gecco.2023.e02463",
    "type": "journal-article"
  },
  {
    "title": "Ecological Civilization in the making: the ‘construction’ of China’s climate-forestry nexus",
    "authors": [
      "Jin Qian"
    ],
    "year": 2022,
    "venue": "Environmental Sociology",
    "doi": "10.1080/23251042.2022.2124623",
    "url": "http://dx.doi.org/10.1080/23251042.2022.2124623",
    "type": "journal-article"
  }
]
